liquidai_cli/__init__.py
liquidai_cli/cli.py
liquidai_cli/commands/__init__.py
liquidai_cli/commands/config.py
liquidai_cli/commands/db.py
liquidai_cli/commands/infra.py
liquidai_cli/commands/model.py
liquidai_cli/commands/stack.py
liquidai_cli/docker_compose_files/docker-compose.yaml
liquidai_cli/utils/__init__.py
liquidai_cli/utils/config.py
liquidai_cli/utils/device.py
liquidai_cli/utils/docker.py
liquidai_cli/utils/prompt.py
liquidai_cli-0.0.1b0.dist-info/METADATA
liquidai_cli-0.0.1b0.dist-info/WHEEL
liquidai_cli-0.0.1b0.dist-info/entry_points.txt
liquidai_cli-0.0.1b0.dist-info/RECORD
