Metadata-Version: 2.4
Name: liquidai-cli
Version: 0.0.1b0
Summary: CLI tool for Liquid Labs on-prem stack
Author: Liquid Labs
License-Expression: MIT
Requires-Python: >=3.10
Requires-Dist: docker>=6.1.0
Requires-Dist: ruamel-yaml>=0.17.21
Requires-Dist: typer>=0.9.0
Provides-Extra: test
Requires-Dist: pytest-cov>=4.0.0; extra == 'test'
Requires-Dist: pytest-mock>=3.10.0; extra == 'test'
Requires-Dist: pytest>=7.0.0; extra == 'test'
